owui_pipelines/__init__.py
owui_pipelines/api/__init__.py
owui_pipelines/api/azure_agent.py
owui_pipelines/cli/__init__.py
owui_pipelines/cli/main.py
owui_pipelines/models/__init__.py
owui_pipelines/utils/__init__.py
owui_pipelines-0.1.4.dist-info/METADATA
owui_pipelines-0.1.4.dist-info/WHEEL
owui_pipelines-0.1.4.dist-info/entry_points.txt
owui_pipelines-0.1.4.dist-info/top_level.txt
owui_pipelines-0.1.4.dist-info/RECORD
