Metadata-Version: 2.2
Name: owui-pipelines
Version: 0.1.4
Summary: Package for OWUI pipelines
Requires-Python: >=3.11
Requires-Dist: azure-ai-projects>=1.0.0b7
Requires-Dist: azure-ai-resources>=1.0.0b9
Requires-Dist: azure-identity>=1.21.0
Requires-Dist: python-dotenv>=1.0.1
